pythonhere/__init__.py
pythonhere/android_here.py
pythonhere/enum_here.py
pythonhere/exception_manager_here.py
pythonhere/launcher_here.py
pythonhere/main.py
pythonhere/network_here.py
pythonhere/patches_here.py
pythonhere/server_here.py
pythonhere/version_here.py
pythonhere/window_here.py
pythonhere/magic_here/__init__.py
pythonhere/magic_here/shortcuts.py
pythonhere/ui_here/__init__.py
pythonhere/ui_here/connection_address_here.py
pythonhere/ui_here/layout_here.py
pythonhere/ui_here/server_screen_here.py
pythonhere/ui_here/settings_here.py
pythonhere-0.1.5.2.dist-info/LICENSE
pythonhere-0.1.5.2.dist-info/METADATA
pythonhere-0.1.5.2.dist-info/WHEEL
pythonhere-0.1.5.2.dist-info/top_level.txt
pythonhere-0.1.5.2.dist-info/RECORD
