Metadata-Version: 2.1
Name: pythonhere
Version: 0.1.5.2
Summary: Here is the Kivy based app to run code from the Jupyter magic %there
Home-page: https://github.com/b3b/ipython-pythonhere
Author: b3b
Author-email: ash.b3b@gmail.com
License: MIT
Project-URL: Changelog, https://github.com/b3b/pythonhere/blob/master/CHANGELOG.rst
Keywords: android ipython jupyter magic kivy
Platform: UNKNOWN
Classifier: Development Status :: 3 - Alpha
Classifier: Programming Language :: Python :: 3.7
Classifier: Programming Language :: Python :: 3.8
Requires-Dist: kivy (>=2.0.0)
Requires-Dist: herethere (<0.2.0,>=0.1.0)
Requires-Dist: ifaddr
Requires-Dist: ipython
Requires-Dist: ipywidgets
Requires-Dist: nest-asyncio
Requires-Dist: Pillow
Provides-Extra: dev
Requires-Dist: black ; extra == 'dev'
Requires-Dist: codecov ; extra == 'dev'
Requires-Dist: docutils ; extra == 'dev'
Requires-Dist: flake8 ; extra == 'dev'
Requires-Dist: jupytext ; extra == 'dev'
Requires-Dist: pylint ; extra == 'dev'
Requires-Dist: pytest ; extra == 'dev'
Requires-Dist: pytest-asyncio ; extra == 'dev'
Requires-Dist: pytest-cov ; extra == 'dev'
Requires-Dist: pytest-mock ; extra == 'dev'
Provides-Extra: docker
Requires-Dist: jupytext (==1.7.1) ; extra == 'docker'
